{
  "total_pages": 1,
  "page": 1,
  "page_size": 100,
  "message": "success",
  "timestamp": 0,
  "data": [
    {
      "id": 0,
      "name": "Sugar",
      "singer": "Maroon 5",
      "src_url": "Maroon 5 - Sugar.flac",
      "lyric_url": null
    },
    {
      "id": 1,
      "name": "Try",
      "singer": "Marlisa",
      "src_url": "Marlisa - Try.mp3",
      "lyric_url": "Marlisa - Try.lrc"
    },
    {
      "id": 2,
      "name": "Solo Dance",
      "singer": "Martin Jensen",
      "src_url": "Martin Jensen - Solo Dance.flac",
      "lyric_url": "Martin Jensen - Solo Dance.lrc"
    },
    {
      "id": 3,
      "name": "One Day",
      "singer": "MatisYahu",
      "src_url": "MatisYahu - One Day.flac",
      "lyric_url": "MatisYahu - One Day.lrc"
    },
    {
      "id": 4,
      "name": "Sold Out",
      "singer": "Hawk Nelson",
      "src_url": "Hawk Nelson - Sold Out.flac",
      "lyric_url": "Hawk Nelson - Sold Out.lrc"
    },
    {
      "id": 5,
      "name": "喜欢你",
      "singer": "G.E.M. 邓紫棋",
      "src_url": "G.E.M. 邓紫棋 - 喜欢你.flac",
      "lyric_url": "G.E.M. 邓紫棋 - 喜欢你.lrc"
    },
    {
      "id": 6,
      "name": "Wake (Studio)",
      "singer": "Hillsong Young & Free",
      "src_url": "Hillsong Young & Free - Wake (Studio).flac",
      "lyric_url": "Hillsong Young & Free - Wake (Studio).lrc"
    },
    {
      "id": 7,
      "name": "Get Ready For It",
      "singer": "Take That",
      "src_url": "Take That - Get Ready For It.flac",
      "lyric_url": "Take That - Get Ready For It.lrc"
    },
    {
      "id": 8,
      "name": "哈尼宝贝",
      "singer": "南征北战NZBZ",
      "src_url": "南征北战NZBZ - 哈尼宝贝.flac",
      "lyric_url": "南征北战NZBZ - 哈尼宝贝.lrc"
    },
    {
      "id": 9,
      "name": "白月光与朱砂痣",
      "singer": "大籽",
      "src_url": "大籽 - 白月光与朱砂痣.flac",
      "lyric_url": "大籽 - 白月光与朱砂痣.lrc"
    },
    {
      "id": 10,
      "name": "兄弟干杯",
      "singer": "庞龙",
      "src_url": "庞龙 - 兄弟干杯.flac",
      "lyric_url": "庞龙 - 兄弟干杯.lrc"
    },
    {
      "id": 11,
      "name": "Counting Stars",
      "singer": "OneRepublic",
      "src_url": "OneRepublic - Counting Stars.flac",
      "lyric_url": "OneRepublic - Counting Stars.lrc"
    },
    {
      "id": 12,
      "name": "流星",
      "singer": "",
      "src_url": "流星完整版.mp3",
      "lyric_url": null
    }
  ]
}
